[
  {
    "line": 1,
    "elements": [
      {
        "line": 3,
        "name": "",
        "description": "",
        "type": "background",
        "keyword": "Background",
        "steps": [
          {
            "result": {
              "duration": 3844985040,
              "status": "passed"
            },
            "line": 4,
            "name": "Open the browser",
            "match": {
              "location": "stepDefinition.Open_the_browser()"
            },
            "keyword": "Given "
          },
          {
            "result": {
              "duration": 11650763649,
              "status": "passed"
            },
            "line": 5,
            "name": "Navigate to the \"http://shop.ng.unicityqa.com/master/#/home\" application",
            "match": {
              "arguments": [
                {
                  "val": "http://shop.ng.unicityqa.com/master/#/home",
                  "offset": 17
                }
              ],
              "location": "stepDefinition.navigate_to_the_application(String)"
            },
            "keyword": "And "
          }
        ]
      },
      {
        "line": 15,
        "name": "Shopping Cart Applciation Order Submit",
        "description": "",
        "id": "application-login;shopping-cart-applciation-order-submit;;2",
        "type": "scenario",
        "keyword": "Scenario Outline",
        "steps": [
          {
            "result": {
              "duration": 10652697303,
              "status": "passed"
            },
            "line": 8,
            "name": "user enters 108639101 and 1234 to login",
            "match": {
              "arguments": [
                {
                  "val": "108639101",
                  "offset": 12
                },
                {
                  "val": "1234",
                  "offset": 26
                }
              ],
              "location": "Login.user_enters_and_to_login(String,String)"
            },
            "matchedColumns": [
              0,
              1
            ],
            "keyword": "When "
          },
          {
            "result": {
              "duration": 15830262042,
              "status": "passed"
            },
            "line": 9,
            "name": "Check products",
            "match": {
              "location": "Home.Check_products()"
            },
            "keyword": "Then "
          }
        ]
      }
    ],
    "name": "Application Login",
    "description": "",
    "id": "application-login",
    "keyword": "Feature",
    "uri": "Hooks.feature"
  }
]